ragger_sdk/__init__.py
ragger_sdk/client.py
ragger_sdk/constants.py
ragger_sdk/endpoints/__init__.py
ragger_sdk/endpoints/chat_history.py
ragger_sdk/endpoints/documents.py
ragger_sdk/endpoints/index.py
ragger_sdk/endpoints/query.py
ragger_sdk/endpoints/status.py
ragger_sdk/exceptions.py
ragger_python_sdk-0.1.3.dist-info/METADATA
ragger_python_sdk-0.1.3.dist-info/WHEEL
ragger_python_sdk-0.1.3.dist-info/licenses/LICENSE
ragger_python_sdk-0.1.3.dist-info/RECORD
