Metadata-Version: 2.4
Name: ragger-python-sdk
Version: 0.1.3
Summary: Python SDK for ragger.ai RAG API
License: MIT
License-File: LICENSE
Keywords: rag,retrieval,augmented,generation,ai,llm,nlp,vector,search,embeddings,semantic-search,document-processing
Author: Ragger Team
Author-email: support@ragger.ai
Requires-Python: >=3.9,<4.0
Classifier: Development Status :: 3 - Alpha
Classifier: Intended Audience :: Developers
Classifier: License :: OSI Approved :: MIT License
Classifier: Operating System :: OS Independent
Classifier: Programming Language :: Python :: 3
Classifier: Programming Language :: Python :: 3.9
Classifier: Programming Language :: Python :: 3.10
Classifier: Programming Language :: Python :: 3.11
Classifier: Programming Language :: Python :: 3.12
Classifier: Programming Language :: Python :: 3.13
Classifier: Programming Language :: Python :: 3.14
Classifier: Programming Language :: Python :: 3.8
Classifier: Topic :: Scientific/Engineering :: Artificial Intelligence
Classifier: Topic :: Software Development :: Libraries :: Python Modules
Classifier: Topic :: Text Processing :: Indexing
Requires-Dist: python-dotenv (>=1.0.0,<2.0.0)
Requires-Dist: requests (>=2.31.0,<3.0.0)
Project-URL: Documentation, https://github.com/RaggerAI/python-sdk#readme
Project-URL: Homepage, https://github.com/RaggerAI/python-sdk
Project-URL: Repository, https://github.com/RaggerAI/python-sdk
